struct_post/__init__.py
struct_post/beam.py
struct_post/coupon.py
struct_post/read_lvm_file.py
struct_post-0.1.8.3.dist-info/licenses/LICENSE
struct_post-0.1.8.3.dist-info/METADATA
struct_post-0.1.8.3.dist-info/WHEEL
struct_post-0.1.8.3.dist-info/top_level.txt
struct_post-0.1.8.3.dist-info/RECORD
